ml_mnist_cnn/__init__.py
ml_mnist_cnn/text_reader.py
ml_mnist_cnn/data/my_code.py
ml_mnist_cnn-0.1.dist-info/METADATA
ml_mnist_cnn-0.1.dist-info/WHEEL
ml_mnist_cnn-0.1.dist-info/top_level.txt
ml_mnist_cnn-0.1.dist-info/RECORD
